{
  "IsEncrypted": false,
  "Values": {
    "AzureWebJobsStorage": "UseDevelopmentStorage=true",
    "FUNCTIONS_WORKER_RUNTIME": "java",
    "TENANT_ID": "e3a46007-31cb-4529-b8cc-1e59b97ebdbd",
    "ISSUER": "https://login.microsoftonline.com/e3a46007-31cb-4529-b8cc-1e59b97ebdbd/v2.0",
    "POSTGRESQL_SERVER": "tekv-db-server.postgres.database.azure.com:5432",
    "POSTGRESQL_USER": "tekvdbadmin@tekv-db-server",
    "POSTGRESQL_PWD": "MhZJh94z9D3Db3vW",
    "POSTGRESQL_SECURITY_MODE": "?ssl=true&sslmode=require",
    "ENVIRONMENT_NAME": "dev",
    "EMAIL_INVITE_CLIENT_ID": "353f505a-d4be-442f-bc22-c016c59132c9",
    "EMAIL_INVITE_CLIENT_SECRET": "jan8Q~eRD-MDTWMHAqNUGmvD..LuPNPEajcS9bev",
    "DASHBOARD_APP_CLIENT_ID": "928c5e82-089b-4c3d-8080-29a4008bcccb",
    "DASHBOARD_APP_SECRET_ID": "72h8Q~eEuk1F6ZhZ6z1xmtGQd_-r94a3QuPMaday",
    "STORAGE_ACCOUNT_NAME": "lswebappstorage",
    "STORAGE_CONTAINER_NAME": "spotlight",
    "SMTP_USER": "spotlight-integration@tekvizion.com",
    "SMTP_PWD": "G9um3XGr",
    "SMTP_HOST": "exchange.tekvizion.com",
    "NOTIFICATIONS_ENDPOINT": "https://fcm.googleapis.com/fcm/send",
    "NOTIFICATIONS_AUTH_KEY": "key=AAAAZQriFSg:APA91bEaRPdifNydaU1p88GVMXOsempGA7DeNl27zpt9941BJnyeXWwz8OYpKKd7nbuLXred8q5R5P0DmGsPA9Q3MXo8Lxk_RhpzaM3sUsZsB1tNeSG9D70PIl_eP5ilSanm-N4cU-Rs",
    "TAP_USERNAME": "spotlight@tekvizion.com",
    "TAP_PASSWORD": "spotlight123",
    "SUB_ACCOUNT_ADMIN_ANDROID": "test-spotlight-subaccount-admin@tekvizionlabs.com",
    "SUB_ACCOUNT_ADMIN_IOS": "test-functional-subaccount-admin@tekvizionlabs.com",
      "GEO_CODE_API_KEY": "AAPKbcb7790d07d44f45b22761d4120bcabbsYqk6SpLHbk2fv4uwscansCTMuLM2PK39IutypfBaZ0pAeCt6koQYDbsy6T4wMUX"
  },
  "Host": {
    "LocalHttpPort": 7071,
    "CORS": "*"
  }
}
